README.md
setup.py
liveboxplaytv/__init__.py
liveboxplaytv/channels.py
liveboxplaytv/cli.py
liveboxplaytv/keys.py
liveboxplaytv/liveboxplaytv.py
liveboxplaytv.egg-info/PKG-INFO
liveboxplaytv.egg-info/SOURCES.txt
liveboxplaytv.egg-info/dependency_links.txt
liveboxplaytv.egg-info/entry_points.txt
liveboxplaytv.egg-info/requires.txt
liveboxplaytv.egg-info/top_level.txt