Metadata-Version: 2.1
Name: liveboxplaytv
Version: 2.0.3
Summary: Python bindings for the Orange Livebox Play TV appliance
Home-page: https://github.com/pschmitt/python-liveboxplaytv
Author: Philipp Schmitt
Author-email: philipp@schmitt.co
License: GPL3
Platform: UNKNOWN
